therepl/__init__.py
therepl/log.py
therepl/rpc.py
therepl/utils.py
therepl-0.2.0.dist-info/WHEEL
therepl-0.2.0.dist-info/METADATA
therepl-0.2.0.dist-info/RECORD
